pglogmon/__init__.py
pglogmon/main.py
pglogmon/version.txt
pglogmon-1.0.0.dist-info/DESCRIPTION.rst
pglogmon-1.0.0.dist-info/METADATA
pglogmon-1.0.0.dist-info/RECORD
pglogmon-1.0.0.dist-info/WHEEL
pglogmon-1.0.0.dist-info/entry_points.txt
pglogmon-1.0.0.dist-info/metadata.json
pglogmon-1.0.0.dist-info/top_level.txt
